{
    "items": [{
            "name": "item 1",
            "price": "50",
            "userId": "10s15965808dd26396590158",
            "id": "52ddc3e8-1180-42c3-805e-9faad112ecca"
        },
        {
            "name": "item 2",
            "price": "60",
            "userId": "101596580826396590158",
            "id": "1ee6c446-57d0-4b2f-96f0-710b99728d3a"
        },
        {
            "name": "item 2",
            "price": "60",
            "userId": "notme",
            "id": "1ee6c446-57d0-4b2f-96f0-710b99728d3a"
        },
        {
            "name": "Free Donut",
            "price": 55,
            "userId": "101596580826396590158",
            "id": "6aff05ae-aa16-427d-bc38-7278e52b2e4c"
        },
        {
            "name": "hello world",
            "price": 1100,
            "userId": "101596580826396590158",
            "id": "bb9f85dc-f62e-4260-8a2e-4734820c3cfd"
        },
        {
            "name": "free donut",
            "price": 50,
            "userId": "101596580826396590158",
            "id": "0305d0f6-ab9f-4503-8580-268717116511"
        },
        {
            "name": "aa",
            "price": 2,
            "userId": "101596580826396590158",
            "id": "09f03bcd-e7cc-4e9b-97bc-89c3ec88cdde"
        },
        {
            "name": "yummy",
            "price": 50,
            "userId": "101596580826396590158",
            "id": "ad5ecafe-3f92-42d4-98f0-d9f66724b125"
        },
        {
            "name": "laSJlas",
            "price": 1123,
            "userId": "101596580826396590158",
            "id": "234cc9b1-8333-4802-bd8b-a14a7fbe1d26"
        }
    ]
}